CHANGES.txt
LICENSE.txt
README.txt
setup.py
js/__init__.py
js.jquery_tablednd.egg-info/PKG-INFO
js.jquery_tablednd.egg-info/SOURCES.txt
js.jquery_tablednd.egg-info/dependency_links.txt
js.jquery_tablednd.egg-info/entry_points.txt
js.jquery_tablednd.egg-info/namespace_packages.txt
js.jquery_tablednd.egg-info/not-zip-safe
js.jquery_tablednd.egg-info/requires.txt
js.jquery_tablednd.egg-info/top_level.txt
js/jquery_tablednd/__init__.py
js/jquery_tablednd/test_jquery_tablednd.txt
js/jquery_tablednd/resources/jquery.tablednd.js
js/jquery_tablednd/resources/jquery.tablednd.min.js