Metadata-Version: 1.0
Name: js.jquery-tablednd
Version: 0.4
Summary: Fanstatic packaging of jQuery TableDND
Home-page: https://github.com/disko/js.jquery_tablednd
Author: Andreas Kaiser
Author-email: disko@binary-punks.com
License: BSD
Platform: UNKNOWN
